msteams_tickler/__init__.py
msteams_tickler/classic/__init__.py
msteams_tickler/classic/config.py
msteams_tickler/classic/models.py
msteams_tickler/classic/token.py
msteams_tickler/config.py
msteams_tickler/main.py
msteams_tickler/notify.py
msteams_tickler-1.0.1.dist-info/entry_points.txt
msteams_tickler-1.0.1.dist-info/LICENSE
msteams_tickler-1.0.1.dist-info/WHEEL
msteams_tickler-1.0.1.dist-info/METADATA
msteams_tickler-1.0.1.dist-info/RECORD
