Metadata-Version: 2.1
Name: msteams-tickler
Version: 1.0.1
Summary: CLI tool for macOS to check MS Teams token expiration and send notifications
Author: Daniel Tom
Author-email: daniel.tom@xebia.com
Requires-Python: >=3.11,<4.0
Classifier: Programming Language :: Python :: 3
Classifier: Programming Language :: Python :: 3.11
Requires-Dist: binary-cookies-parser (>=0.1.3,<0.2.0)
Requires-Dist: pytz (>=2024.1,<2025.0)
Requires-Dist: sqlmodel (>=0.0.19,<0.0.20)
Requires-Dist: typer-slim (>=0.12.3,<0.13.0)
